[
  {
    "id": "neurotransmitters_001",
    "topic": "neurotransmitters",
    "difficulty": "intermediate",
    "question": "Which neurotransmitter is primarily responsible for muscle contraction?",
    "answers": [
      "Dopamine",
      "Serotonin",
      "Acetylcholine",
      "Norepinephrine"
    ],
    "correct": 2,
    "tags": [
      "neurotransmitters"
    ],
    "stats": {
      "correct": 0,
      "incorrect": 0
    }
  },
  {
    "id": "neurotransmitters_002",
    "topic": "neurotransmitters",
    "difficulty": "intermediate",
    "question": "Which neurotransmitter is associated with mood regulation, appetite, and sleep?",
    "answers": [
      "Dopamine",
      "GABA",
      "Serotonin",
      "Glutamate"
    ],
    "correct": 2,
    "tags": [
      "neurotransmitters"
    ],
    "stats": {
      "correct": 0,
      "incorrect": 0
    }
  },
  {
    "id": "neurotransmitters_003",
    "topic": "neurotransmitters",
    "difficulty": "intermediate",
    "question": "Dopamine plays a significant role in which of the following?",
    "answers": [
      "Muscle contraction",
      "Pain inhibition",
      "Motor control, reward, and motivation",
      "Sleep regulation"
    ],
    "correct": 2,
    "tags": [
      "neurotransmitters"
    ],
    "stats": {
      "correct": 0,
      "incorrect": 0
    }
  },
  {
    "id": "neurotransmitters_004",
    "topic": "neurotransmitters",
    "difficulty": "intermediate",
    "question": "Which neurotransmitter is the main excitatory chemical in the brain?",
    "answers": [
      "GABA",
      "Serotonin",
      "Norepinephrine",
      "Glutamate"
    ],
    "correct": 3,
    "tags": [
      "neurotransmitters"
    ],
    "stats": {
      "correct": 0,
      "incorrect": 0
    }
  },
  {
    "id": "neurotransmitters_005",
    "topic": "neurotransmitters",
    "difficulty": "intermediate",
    "question": "Which neurotransmitter is the most common inhibitory neurotransmitter in the central nervous system?",
    "answers": [
      "GABA",
      "Dopamine",
      "Serotonin",
      "Norepinephrine"
    ],
    "correct": 0,
    "tags": [
      "neurotransmitters"
    ],
    "stats": {
      "correct": 0,
      "incorrect": 0
    }
  },
  {
    "id": "neurotransmitters_006",
    "topic": "neurotransmitters",
    "difficulty": "intermediate",
    "question": "Which neurotransmitter is involved in the fight-or-flight response?",
    "answers": [
      "GABA",
      "Norepinephrine",
      "Dopamine",
      "Acetylcholine"
    ],
    "correct": 1,
    "tags": [
      "neurotransmitters"
    ],
    "stats": {
      "correct": 0,
      "incorrect": 0
    }
  },
  {
    "id": "neurotransmitters_007",
    "topic": "neurotransmitters",
    "difficulty": "intermediate",
    "question": "Low levels of which neurotransmitter are associated with depression?",
    "answers": [
      "Serotonin",
      "Acetylcholine",
      "Dopamine",
      "Glutamate"
    ],
    "correct": 0,
    "tags": [
      "neurotransmitters"
    ],
    "stats": {
      "correct": 0,
      "incorrect": 0
    }
  },
  {
    "id": "neurotransmitters_008",
    "topic": "neurotransmitters",
    "difficulty": "intermediate",
    "question": "What is the primary function of endorphins?",
    "answers": [
      "Stimulate digestion",
      "Regulate mood swings",
      "Block pain and promote a sense of well-being",
      "Trigger reflexes"
    ],
    "correct": 2,
    "tags": [
      "neurotransmitters"
    ],
    "stats": {
      "correct": 0,
      "incorrect": 0
    }
  },
  {
    "id": "neurotransmitters_009",
    "topic": "neurotransmitters",
    "difficulty": "intermediate",
    "question": "Which neurotransmitter helps regulate circadian rhythms and sleep cycles?",
    "answers": [
      "Acetylcholine",
      "Dopamine",
      "Melatonin",
      "Serotonin"
    ],
    "correct": 2,
    "tags": [
      "neurotransmitters"
    ],
    "stats": {
      "correct": 0,
      "incorrect": 0
    }
  },
  {
    "id": "neurotransmitters_010",
    "topic": "neurotransmitters",
    "difficulty": "intermediate",
    "question": "Which neurotransmitter is elevated during alertness and stress responses?",
    "answers": [
      "GABA",
      "Norepinephrine",
      "Serotonin",
      "Dopamine"
    ],
    "correct": 1,
    "tags": [
      "neurotransmitters"
    ],
    "stats": {
      "correct": 0,
      "incorrect": 0
    }
  }
]